<annotation verified="no">
  <folder>Original_Images</folder>
  <filename>BloodImage_00158</filename>
  <path>/Users/cosmic/wbc-classification/Original_Images/BloodImage_00158.jpg</path>
  <source>
    <database>Unknown</database>
  </source>
  <size>
    <width>640</width>
    <height>480</height>
    <depth>3</depth>
  </size>
  <segmented>0</segmented>
  <object>
    <name>Neutrophil</name>
    <pose>Unspecified</pose>
    <truncated>0</truncated>
    <difficult>0</difficult>
    <bndbox>
      <xmin>335</xmin>
      <ymin>212</ymin>
      <xmax>497</xmax>
      <ymax>364</ymax>
    </bndbox>
  </object>
</annotation>
